markupify/__init__.py
markupify/page.py
markupify/tags.py
markupify-1.1.0.dist-info/LICENSE
markupify-1.1.0.dist-info/METADATA
markupify-1.1.0.dist-info/WHEEL
markupify-1.1.0.dist-info/RECORD
